dataclasses_hierarchy/__init__.py
dataclasses_hierarchy-2020.1.dist-info/COPYING
dataclasses_hierarchy-2020.1.dist-info/METADATA
dataclasses_hierarchy-2020.1.dist-info/WHEEL
dataclasses_hierarchy-2020.1.dist-info/top_level.txt
dataclasses_hierarchy-2020.1.dist-info/RECORD
