Metadata-Version: 2.1
Name: dataclasses-hierarchy
Version: 2020.1
Summary: Dataclasses-hierarchy: hierarchies and chained methods for dataclasses
Home-page: https://github.com/ulb-metronu/dataclasses-hierarchy
Author: Cédric Hernaslteens
Author-email: cedric.hernalsteens@ulb.be
License: GNU GENERAL PUBLIC LICENSE
Platform: UNKNOWN
Requires-Python: >=3.7
